q_protocol_telemetry/__init__.py
q_protocol_telemetry/swarm_registry.py
q_protocol_telemetry-0.1.0.dist-info/licenses/LICENSE
q_protocol_telemetry-0.1.0.dist-info/METADATA
q_protocol_telemetry-0.1.0.dist-info/WHEEL
q_protocol_telemetry-0.1.0.dist-info/top_level.txt
q_protocol_telemetry-0.1.0.dist-info/RECORD
