Metadata-Version: 2.4
Name: q-protocol-telemetry
Version: 0.1.0
Summary: A lightweight telemetry and registry protocol for autonomous agent swarms.
Home-page: https://github.com/Phil-Hills/q-protocol-telemetry
Author: Phil Hills (Systems Architect)
Author-email: phil@philhills.ai
Project-URL: Bug Tracker, https://github.com/Phil-Hills/q-protocol-telemetry/issues
Project-URL: Documentation, https://philhills.ai/docs/q-protocol
Classifier: Programming Language :: Python :: 3
Classifier: License :: OSI Approved :: MIT License
Classifier: Operating System :: OS Independent
Classifier: Topic :: System :: Systems Administration
Classifier: Topic :: Software Development :: Libraries :: Python Modules
Classifier: Intended Audience :: Developers
Classifier: Intended Audience :: Science/Research
Requires-Python: >=3.8
License-File: LICENSE
Requires-Dist: typing-extensions>=4.0.0
Dynamic: author
Dynamic: author-email
Dynamic: classifier
Dynamic: description
Dynamic: description-content-type
Dynamic: home-page
Dynamic: license-file
Dynamic: project-url
Dynamic: requires-dist
Dynamic: requires-python
Dynamic: summary
